README.md
setup.py
auth_micro/__init__.py
auth_micro/auth.py
auth_micro/decorators.py
auth_micro/exceptions.py
auth_micro/settings.py
auth_micro/utils.py
auth_micro/views.py
jwtauthmicro.egg-info/PKG-INFO
jwtauthmicro.egg-info/SOURCES.txt
jwtauthmicro.egg-info/dependency_links.txt
jwtauthmicro.egg-info/top_level.txt
jwtauthmicro.egg-info/zip-safe